{
  "schemaVersion": "defracto.fidelity-reducer-execution.receipt.v1",
  "receiptKey": "defracto.receipt.fidelity.reducer.execution.slice-020.v1",
  "status": "blocked",
  "checkedAt": "2026-06-22T00:00:00-04:00",
  "commandKey": "defracto.conveyor.fidelity.achievement.compute.v1",
  "blockedAtStep": "reduceAchievedLevel",
  "blocker": "graph_step_failed",
  "error": "Unsupported primitive operation: fidelity.achieved_level.reduce.v1",
  "verificationStatus": "resolver_fail_closed",
  "completionPosture": "The fidelity evidence matrix primitive now passes; the reducer primitive is the next missing capability."
}
